clearsale/__init__.py
clearsale/api.py
clearsale/entities.py
clearsale/status_options/__init__.py
clearsale/status_options/request.py
clearsale/status_options/response.py
test_clearsale-1.4.dist-info/METADATA
test_clearsale-1.4.dist-info/WHEEL
test_clearsale-1.4.dist-info/top_level.txt
test_clearsale-1.4.dist-info/RECORD
